LICENSE.txt
README.txt
data_example.yaml
demo_chandy_lamport_output.py
demo_sequencer_output.py
net_flow_vizu_dia.py
setup.py
NetFlowVizu.egg-info/PKG-INFO
NetFlowVizu.egg-info/SOURCES.txt
NetFlowVizu.egg-info/dependency_links.txt
NetFlowVizu.egg-info/requires.txt
NetFlowVizu.egg-info/top_level.txt
tests/data_diacritics.yaml
tests/run.py
tests/tests.py