Metadata-Version: 1.0
Name: NetFlowVizu
Version: 0.6
Summary: Network flow visualizer
Home-page: http://www.smallbulb.net/netflowvizu
Author: David Siroky
Author-email: siroky@dasir.cz
License: MIT License
Keywords: network,host,flow,traffic,communication,visualization,dia
Platform: UNKNOWN
Classifier: Development Status :: 4 - Beta
Classifier: Environment :: Console
Classifier: Intended Audience :: Developers
Classifier: Intended Audience :: Education
Classifier: Intended Audience :: Science/Research
Classifier: License :: OSI Approved :: MIT License
Classifier: Programming Language :: Python
Classifier: Topic :: System :: Networking
Classifier: Topic :: Scientific/Engineering :: Information Analysis
Classifier: Topic :: Scientific/Engineering :: Visualization
